whzmodel.py
whzmodel-1.0.dist-info/METADATA
whzmodel-1.0.dist-info/WHEEL
whzmodel-1.0.dist-info/top_level.txt
whzmodel-1.0.dist-info/RECORD
