Metadata-Version: 2.1
Name: whzmodel
Version: 1.0
Summary: A  module for test
Author: whzikaros
Author-email: 1345146183@qq.com
License: MIT
Platform: UNKNOWN
